Vending_Machine/Vending_machine.v
module vending_machine_18105070(
input clk, input rst, input [1:0]in, // 01 = 5 rs, 10 = 10 rs
output reg out, output reg[1:0] change
);

parameter s0 = 2'b00;
parameter s1 = 2'b01;
parameter s2 = 2'b10;

reg[1:0] c_state,n_state;
always@ (posedge clk)
begin
if(rst == 1)
 begin
  c_state = 0;
  n_state = 0;
  change = 2'b00;
 end
else
 c_state = n_state;
case(c_state)
 s0: //state 0 : 0 rs
 if(in == 0)
  begin
   n_state = s0;
   out = 0;
   change = 2'b00;
  end
else if(in == 2'b01)
  begin
   n_state = s1;
   out = 0;
   change = 2'b00;
  end
else if(in == 2'b10)
 begin
  n_state = s2;
  out = 0;
  change = 2'b00;
 end
s1: //state 1 : 5 rs
if(in == 0)
 begin
  n_state = s0;
  out = 0;
  change = 2'b01; //change returned 5 rs
 end
else if(in == 2'b01)
 begin
  n_state = s0;
  out = 1;
  change = 2'b00;
 end
s2: //state 2 : 10 rs
if(in == 0)
 begin
  n_state = s0;
  out = 0;
  change = 2'b10;
 end
else if(in == 2'b01)
 begin
 n_state = s0;
 out = 1;
 change = 2'b00;
 end
else if(in == 2'b10)
 begin
 n_state = s0;
 out = 1;
 change = 2'b01; //change returned 5 rs and 1 bottle
 end
  endcase
 end
endmodule

//testbench
module vending_machine_tb;
//inputs
reg clk;
reg[1:0] in;
reg rst;
//output
wire out;
wire[1:0] change;
vending_machine_18105070 uut(
.clk(clk),
.rst(rst),
.in(in),
.out(out),
.change(change)
);
initial begin
//initialise inputs
$dumpfile("vending_machine_18105070.vcd");
$dumpvars(0,vending_machine_tb);
rst = 1;
clk = 0;
#6 rst = 0;
in = 2;
#19 in = 2;
#25 $finish;

end
always #5 clk = ~clk;
endmodule

Vending_Machine/vending_machine_18105070.vcd
$date
	Sun May 29 14:44:39 2022
$end
$version
	ModelSim Version 2020.4
$end
$timescale
	1ns
$end

$scope module vending_machine_tb $end
$var reg 1 ! clk $end
$var reg 2 " in [1:0] $end
$var reg 1 # rst $end
$var wire 1 $ out $end
$var wire 1 % change [1] $end
$var wire 1 & change [0] $end

$scope module uut $end
$var parameter 2 ' s0 $end
$var parameter 2 ( s1 $end
$var parameter 2 ) s2 $end
$var wire 1 * clk $end
$var wire 1 + rst $end
$var wire 1 , in [1] $end
$var wire 1 - in [0] $end
$var reg 1 . out $end
$var reg 2 / change [1:0] $end
$var reg 2 0 c_state [1:0] $end
$var reg 2 1 n_state [1:0] $end
$upscope $end
$upscope $end
$enddefinitions $end
#0
$dumpvars
0!
bx "
1#
x.
bx /
bx 0
bx 1
b0 '
b1 (
b10 )
x$
x&
x%
x-
x,
1+
0*
$end
#5
1!
1*
b0 0
b0 1
b0 /
0&
0%
#6
0#
b10 "
0+
0-
1,
#10
0!
0*
#15
1!
1*
b10 1
0.
0$
#20
0!
0*
#25
1!
1*
b10 0
b0 1
1.
b1 /
1$
1&
#30
0!
0*
#35
1!
1*
b0 0
b10 1
0.
b0 /
0$
0&
#40
0!
0*
#45
1!
1*
b10 0
b0 1
1.
b1 /
1$
1&
#50
0!
0*
#55
1!
1*
b0 0
b10 1
0.
b0 /
0$
0&
#60
0!
0*
#65
1!
1*
b10 0
b0 1
1.
b1 /
1$
1&
#70
0!
0*
#75
1!
1*
b0 0
b10 1
0.
b0 /
0$
0&
#80
0!
0*
#85
1!
1*
b10 0
b0 1
1.
b1 /
1$
1&
#90
0!
0*
#95
1!
1*
b0 0
b10 1
0.
b0 /
0$
0&
#100
0!
0*
#105
1!
1*
b10 0
b0 1
1.
b1 /
1$
1&
#110
0!
0*
#115
1!
1*
b0 0
b10 1
0.
b0 /
0$
0&
#120
0!
0*
#125
1!
1*
b10 0
b0 1
1.
b1 /
1$
1&
#130
0!
0*
#135
1!
1*
b0 0
b10 1
0.
b0 /
0$
0&
#140
0!
0*
#145
1!
1*
b10 0
b0 1
1.
b1 /
1$
1&
#150
0!
0*
#155
1!
1*
b0 0
b10 1
0.
b0 /
0$
0&
#160
0!
0*
#165
1!
1*
b10 0
b0 1
1.
b1 /
1$
1&
#170
0!
0*
#175
1!
1*
b0 0
b10 1
0.
b0 /
0$
0&
#180
0!
0*
#185
1!
1*
b10 0
b0 1
1.
b1 /
1$
1&
#190
0!
0*
#195
1!
1*
b0 0
b10 1
0.
b0 /
0$
0&
#200
0!
0*
#205
1!
1*
b10 0
b0 1
1.
b1 /
1$
1&
#210
0!
0*
#215
1!
1*
b0 0
b10 1
0.
b0 /
0$
0&
#220
0!
0*
#225
1!
1*
b10 0
b0 1
1.
b1 /
1$
1&
#230
0!
0*
#235
1!
1*
b0 0
b10 1
0.
b0 /
0$
0&
#240
0!
0*
#245
1!
1*
b10 0
b0 1
1.
b1 /
1$
1&
